kvd/__init__.py
kvd/kvstore_client.py
kvd/store.py
kvd-0.1.0.dist-info/LICENSE
kvd-0.1.0.dist-info/WHEEL
kvd-0.1.0.dist-info/METADATA
kvd-0.1.0.dist-info/RECORD
